scripts/__init__.py
scripts/sascore_bench/__init__.py
scripts/sascore_bench/config.yaml
scripts/sascore_bench/plot_results.py
scripts/sascore_bench/run_benchmark.py
synplan/__init__.py
synplan/chem/__init__.py
synplan/chem/precursor.py
synplan/chem/rdkit_utils.py
synplan/chem/reaction.py
synplan/chem/utils.py
synplan/chem/data/__init__.py
synplan/chem/data/filtering.py
synplan/chem/data/standardizing.py
synplan/chem/reaction_routes/__init__.py
synplan/chem/reaction_routes/clustering.py
synplan/chem/reaction_routes/io.py
synplan/chem/reaction_routes/leaving_groups.py
synplan/chem/reaction_routes/route_cgr.py
synplan/chem/reaction_routes/visualisation.py
synplan/chem/reaction_rules/__init__.py
synplan/chem/reaction_rules/extraction.py
synplan/chem/reaction_rules/manual/__init__.py
synplan/chem/reaction_rules/manual/decompositions.py
synplan/chem/reaction_rules/manual/transformations.py
synplan/interfaces/__init__.py
synplan/interfaces/cli.py
synplan/interfaces/gui.py
synplan/mcts/__init__.py
synplan/mcts/algorithm.py
synplan/mcts/evaluation.py
synplan/mcts/expansion.py
synplan/mcts/node.py
synplan/mcts/search.py
synplan/mcts/tree.py
synplan/ml/__init__.py
synplan/ml/networks/__init__.py
synplan/ml/networks/modules.py
synplan/ml/networks/policy.py
synplan/ml/networks/value.py
synplan/ml/training/__init__.py
synplan/ml/training/preprocessing.py
synplan/ml/training/reinforcement.py
synplan/ml/training/supervised.py
synplan/utils/__init__.py
synplan/utils/config.py
synplan/utils/files.py
synplan/utils/loading.py
synplan/utils/logging.py
synplan/utils/parallel.py
synplan/utils/visualisation.py
synplanner-1.3.2.dist-info/METADATA
synplanner-1.3.2.dist-info/WHEEL
synplanner-1.3.2.dist-info/entry_points.txt
synplanner-1.3.2.dist-info/licenses/LICENSE
synplanner-1.3.2.dist-info/RECORD
