Metadata-Version: 2.4
Name: SynPlanner
Version: 1.3.2
Summary: Toolbox for chemical synthesis planning
Author-email: Laboratoire de Chemoinformatique <tagirshin@gmail.com>
License: MIT
License-File: LICENSE
Requires-Python: <3.13,>=3.10
Requires-Dist: adabelief-pytorch>=0.2.1
Requires-Dist: cgrtools-stable==4.2.13
Requires-Dist: chython-synplan>=1.91
Requires-Dist: chytorch-rxnmap-synplan>=1.6
Requires-Dist: chytorch-synplan>=1.69
Requires-Dist: click>=8.0.0
Requires-Dist: huggingface-hub>=0.24.0
Requires-Dist: ipykernel>6.29.0
Requires-Dist: ipywidgets>8.1.0
Requires-Dist: matplotlib>=3.10.8
Requires-Dist: numpy>=2
Requires-Dist: pandas>=1.4
Requires-Dist: pytorch-lightning>=2
Requires-Dist: pyyaml>=6.0
Requires-Dist: ray>=2.0
Requires-Dist: rdkit>2025.3.5
Requires-Dist: streamlit-ketcher>=0.0.1
Requires-Dist: streamlit>1.35.1
Requires-Dist: torch-geometric>=2.4.0
Requires-Dist: toytree>=2.0
Provides-Extra: cpu
Requires-Dist: torch>=2.0; extra == 'cpu'
Provides-Extra: cuda
Requires-Dist: torch>=2.0; extra == 'cuda'
